[
  {
    "id": "going-merry",
    "name": "Going Merry",
    "type": "Caravel",
    "debutEpisode": 17,
    "episodeAppearances": [67],
    "owner": {
      "crewId": "straw-hat-pirates",
      "startEpisode": 17
    },
    "keyMoments": [
      {
        "episodeNumber": 67,
        "timestamp": "05:45",
        "eventId": "ep067-event-003",
        "description": "Miss All Sunday mysteriously infiltrates the Going Merry without being detected, appearing on the ship to confront the crew.",
        "significance": "Demonstrates that even the crew's home and sanctuary can be breached, emphasizing the danger posed by skilled enemies."
      },
      {
        "episodeNumber": 67,
        "timestamp": "14:25",
        "eventId": "ep067-event-008",
        "description": "Luffy destroys the Eternal Pose on the deck of the Going Merry, making his defining declaration about the crew's independence.",
        "significance": "The Going Merry serves as the setting for one of Luffy's most iconic character moments, reinforcing the ship as a symbol of the crew's freedom."
      },
      {
        "episodeNumber": 67,
        "timestamp": "16:40",
        "eventId": "ep067-event-009",
        "description": "The Going Merry departs Whisky Peak with Vivi and Karoo aboard, setting course for Little Garden.",
        "significance": "The ship carries the crew and their new companions into the next stage of their journey through the Grand Line."
      }
    ]
  }
]
