[
  {
    "url": "https://onepiece.fandom.com/wiki/Episode_111",
    "title": "Episode 111 - One Piece Wiki",
    "platform": "Fandom Wiki",
    "author": "One Piece Wiki Contributors",
    "accessedAt": "2025-11-18",
    "reliability": "HIGH",
    "sourceType": "WIKI",
    "informationType": "Episode details, plot summary, production credits, manga chapters adapted"
  },
  {
    "url": "https://onepiece.fandom.com/wiki/Chapter_179",
    "title": "Chapter 179 - One Piece Wiki",
    "platform": "Fandom Wiki",
    "author": "One Piece Wiki Contributors",
    "accessedAt": "2025-11-18",
    "reliability": "HIGH",
    "sourceType": "WIKI",
    "informationType": "Manga chapter details and events adapted in Episode 111"
  },
  {
    "url": "https://onepiece.fandom.com/wiki/Chapter_180",
    "title": "Chapter 180 - One Piece Wiki",
    "platform": "Fandom Wiki",
    "author": "One Piece Wiki Contributors",
    "accessedAt": "2025-11-18",
    "reliability": "HIGH",
    "sourceType": "WIKI",
    "informationType": "Manga chapter details and events adapted in Episode 111"
  },
  {
    "url": "https://www.imdb.com/title/tt0987444/",
    "title": "One Piece - Kiseki e no Shissou! Arabasta Doubutsu Land (TV Episode 2002)",
    "platform": "IMDb",
    "author": "IMDb Contributors",
    "accessedAt": "2025-11-18",
    "reliability": "HIGH",
    "sourceType": "DATABASE",
    "informationType": "Episode air date, ratings, and basic information"
  },
  {
    "url": "https://onepiece.fandom.com/wiki/Super_Spot-Billed_Duck_Troops",
    "title": "Super Spot-Billed Duck Troops - One Piece Wiki",
    "platform": "Fandom Wiki",
    "author": "One Piece Wiki Contributors",
    "accessedAt": "2025-11-18",
    "reliability": "HIGH",
    "sourceType": "WIKI",
    "informationType": "Character debut and details about the Super Spot-Billed Duck Troops"
  },
  {
    "url": "https://onepiece.fandom.com/wiki/Pell",
    "title": "Pell - One Piece Wiki",
    "platform": "Fandom Wiki",
    "author": "One Piece Wiki Contributors",
    "accessedAt": "2025-11-18",
    "reliability": "HIGH",
    "sourceType": "WIKI",
    "informationType": "Character information, Devil Fruit abilities, and role in Alabasta arc"
  },
  {
    "url": "https://www.cbr.com/one-piece-luffy-vs-croc-battles-winner-loser/",
    "title": "Every Luffy Vs. Crocodile Fight in One Piece & The Winner",
    "platform": "CBR",
    "author": "CBR Staff",
    "accessedAt": "2025-11-18",
    "reliability": "MEDIUM",
    "sourceType": "ARTICLE",
    "informationType": "Analysis of Luffy vs Crocodile battles including the quicksand scene"
  },
  {
    "url": "https://gamerant.com/one-piece-should-luffy-have-lost-to-crocodile/",
    "title": "One Piece: Should Luffy Have Lost To Crocodile?",
    "platform": "GameRant",
    "author": "GameRant Staff",
    "accessedAt": "2025-11-18",
    "reliability": "MEDIUM",
    "sourceType": "ARTICLE",
    "informationType": "Discussion and analysis of the Crocodile vs Luffy fights"
  },
  {
    "url": "https://onepiece.fandom.com/wiki/One_Piece_Music",
    "title": "One Piece Music - One Piece Wiki",
    "platform": "Fandom Wiki",
    "author": "One Piece Wiki Contributors",
    "accessedAt": "2025-11-18",
    "reliability": "HIGH",
    "sourceType": "WIKI",
    "informationType": "Opening and ending song information for Episode 111"
  },
  {
    "url": "https://en.wikipedia.org/wiki/One_Piece_(season_4)",
    "title": "One Piece (season 4) - Wikipedia",
    "platform": "Wikipedia",
    "author": "Wikipedia Contributors",
    "accessedAt": "2025-11-18",
    "reliability": "HIGH",
    "sourceType": "WIKI",
    "informationType": "Season information, episode list, and air dates"
  },
  {
    "url": "https://fandomwire.com/every-one-piece-character-connected-to-the-void-century-ranked/",
    "title": "Every One Piece Character Connected to the Void Century, Ranked",
    "platform": "FandomWire",
    "author": "FandomWire Staff",
    "accessedAt": "2025-11-18",
    "reliability": "MEDIUM",
    "sourceType": "ARTICLE",
    "informationType": "Analysis of Will of D and Void Century connections including Robin's question"
  },
  {
    "url": "https://wiki.sportskeeda.com/one-piece/who-is-pell-in-one-piece",
    "title": "Who is Pell in One Piece?",
    "platform": "Sportskeeda Wiki",
    "author": "Sportskeeda Contributors",
    "accessedAt": "2025-11-18",
    "reliability": "MEDIUM",
    "sourceType": "WIKI",
    "informationType": "Character profile and analysis of Pell"
  }
]
